{"id":"E14000795","title":"Liverpool, Wavertree","demographics":{"withdegree":18.56,"2015UKIP":8.24,"age18-29":22.47,"leave":35.85},"elections":{"2017-06-08":{"type":"general","mp":"Luciana Berger","party":{"code":"Lab"},"electorate":62411,"turnout":{"pc":70.1,"value":43759},"valid":43640,"invalid":119,"majority":29466,"candidates":[{"name":"Luciana Berger","party":{"code":"Lab","title":"Labour and Co-operative"},"votes":34717},{"name":"Denise Haddad","party":{"code":"Con","title":"Conservative"},"votes":5251},{"name":"Richard Kemp","party":{"code":"LD","title":"Liberal Democrat"},"votes":2858},{"name":"Ted Grant","party":{"code":"Green","title":"Green"},"votes":598},{"name":"Adam Heatherington","party":{"code":"Ind","title":"Independent"},"votes":216}]},"2015-05-07":{"type":"general","mp":"Luciana Berger","party":{"code":"Lab","title":"Labour and Co-operative"},"electorate":61549,"turnout":{"pc":66.8,"value":41136},"valid":40974,"invalid":162,"majority":24303},"2019-12-12":{"type":"general","mp":"Paula Barker","party":{"code":"Lab","title":"Labour Party"},"majority":27085,"valid":43377,"turnout":{"value":43377,"pc":68.4},"electorate":63458,"candidates":[{"id":"6881","name":"Adam Heatherington","party":{"code":"Brexit","title":"The Brexit Party"},"img":"https://ge2019.odileeds.org/candidate/6881.jpg","votes":1921,"change":4.4,"share":4.4},{"id":"7681","name":"Richard Kemp","party":{"code":"LD","title":"Liberal Democrats"},"img":"https://ge2019.odileeds.org/candidate/7681.jpg","votes":4055,"change":2.8,"share":9.3},{"id":"49755","name":"Kay Inckle","party":{"code":"Green","title":"Green Party"},"img":"https://ge2019.odileeds.org/candidate/49755.jpg","votes":1365,"change":1.7,"share":3.1},{"id":"51203","name":"Mick Coyne","party":{"code":"Liberal","title":"The Liberal Party"},"img":"https://ge2019.odileeds.org/candidate/51203.jpg","votes":501,"change":1.2,"share":1.2},{"id":"71518","name":"Paula Barker","party":{"code":"Lab","title":"Labour Party"},"img":"https://ge2019.odileeds.org/candidate/71518.jpg","votes":31310,"change":-7.4,"share":72.2},{"id":"72319","name":"Catherine Mulhern","party":{"code":"Con","title":"Conservative and Unionist Party"},"img":"https://ge2019.odileeds.org/candidate/72319.jpg","votes":4225,"change":-2.3,"share":9.7}],"incumbent":{"mp":"Luciana Berger","party":{"code":"Ind","title":"Independent"}}}},"events":[{"date":"2019-12-13T05:50:53.317Z","message":"Liverpool, Wavertree: Lab HOLD"}]}